doc/__init__.py
doc/conf.py
pydocumentdb/__init__.py
pydocumentdb/auth.py
pydocumentdb/base.py
pydocumentdb/consistent_hash_ring.py
pydocumentdb/constants.py
pydocumentdb/default_retry_policy.py
pydocumentdb/document_client.py
pydocumentdb/documents.py
pydocumentdb/endpoint_discovery_retry_policy.py
pydocumentdb/errors.py
pydocumentdb/global_endpoint_manager.py
pydocumentdb/hash_partition_resolver.py
pydocumentdb/http_constants.py
pydocumentdb/murmur_hash.py
pydocumentdb/partition.py
pydocumentdb/query_iterable.py
pydocumentdb/range.py
pydocumentdb/range_partition_resolver.py
pydocumentdb/resource_throttle_retry_policy.py
pydocumentdb/retry_options.py
pydocumentdb/retry_utility.py
pydocumentdb/runtime_constants.py
pydocumentdb/session.py
pydocumentdb/synchronized_request.py
pydocumentdb/utils.py
pydocumentdb/execution_context/__init__.py
pydocumentdb/execution_context/aggregators.py
pydocumentdb/execution_context/base_execution_context.py
pydocumentdb/execution_context/document_producer.py
pydocumentdb/execution_context/endpoint_component.py
pydocumentdb/execution_context/execution_dispatcher.py
pydocumentdb/execution_context/multi_execution_aggregator.py
pydocumentdb/execution_context/query_execution_info.py
pydocumentdb/routing/__init__.py
pydocumentdb/routing/collection_routing_map.py
pydocumentdb/routing/routing_map_provider.py
pydocumentdb/routing/routing_range.py
pydocumentdb-2.3.4.dist-info/METADATA
pydocumentdb-2.3.4.dist-info/RECORD
pydocumentdb-2.3.4.dist-info/WHEEL
pydocumentdb-2.3.4.dist-info/top_level.txt
