Metadata-Version: 2.1
Name: pydocumentdb
Version: 2.3.4
Summary: Azure DocumentDB Python SDK
Home-page: https://github.com/Azure/azure-documentdb-python
Author: Microsoft
Author-email: askdocdb@microsoft.com
Maintainer: Microsoft
Maintainer-email: askdocdb@microsoft.com
License: MIT
Platform: UNKNOWN
Classifier: License :: OSI Approved :: MIT License
Classifier: Intended Audience :: Developers
Classifier: Natural Language :: English
Classifier: Operating System :: OS Independent
Classifier: Programming Language :: Python
Classifier: Programming Language :: Python :: 2.7
Classifier: Programming Language :: Python :: 3.3
Classifier: Programming Language :: Python :: 3.4
Classifier: Programming Language :: Python :: 3.5
Classifier: Programming Language :: Python :: Implementation :: CPython
Classifier: Topic :: Software Development :: Libraries :: Python Modules
Requires-Dist: six (>=1.6)
Requires-Dist: requests (>=2.10.0)
